{
	"info": {
		"_postman_id": "e7adb399-8373-41ac-9871-1a736b5b7c20",
		"name": "Madeira - Backend",
		"schema": "https://schema.getpostman.com/json/collection/v2.1.0/collection.json",
		"_exporter_id": "17378029"
	},
	"item": [
		{
			"name": "Nota Fiscal",
			"item": [
				{
					"name": "Nota Fiscal",
					"request": {
						"method": "POST",
						"header": [],
						"body": {
							"mode": "raw",
							"raw": "{\r\n    \"cnpj_cpf_prestador\": \"10490181000569\",\r\n    \"nota_valor\": 992.2,\r\n    \"nota_impostos\": 23,\r\n    \"nota_chave\": \"38921657136821895164871231768222223532453411\",\r\n    \"nota_data_recebimento\": \"2024-05-02 14:23:00\",\r\n    \"nota_data_emissao\": \"2024-05-02 14:23:00\"\r\n}",
							"options": {
								"raw": {
									"language": "json"
								}
							}
						},
						"url": {
							"raw": "http://localhost:8989/api/nota-fiscal",
							"protocol": "http",
							"host": [
								"localhost"
							],
							"port": "8989",
							"path": [
								"api",
								"nota-fiscal"
							]
						}
					},
					"response": []
				},
				{
					"name": "Pegar Nota Fiscal",
					"protocolProfileBehavior": {
						"disableBodyPruning": true
					},
					"request": {
						"method": "GET",
						"header": [],
						"body": {
							"mode": "raw",
							"raw": "{\r\n    \"cnpj_cpf_prestador\": \"10490181000569\",\r\n    \"nota_valor\": 992.2,\r\n    \"nota_impostos\": 23,\r\n    \"nota_chave\": \"38921657136821895164871231768222223532453411\",\r\n    \"nota_data_recebimento\": \"2024-05-02 14:23:00\",\r\n    \"nota_data_emissao\": \"2024-05-02 14:23:00\"\r\n}",
							"options": {
								"raw": {
									"language": "json"
								}
							}
						},
						"url": {
							"raw": "http://localhost:8989/api/nota-fiscal/",
							"protocol": "http",
							"host": [
								"localhost"
							],
							"port": "8989",
							"path": [
								"api",
								"nota-fiscal",
								""
							]
						}
					},
					"response": []
				}
			]
		}
	]
}
